nighthawk/__init__.py
nighthawk/detector.py
nighthawk/prep_feedback.py
nighthawk/probability_calibration_utils.py
nighthawk/run_nighthawk.py
nighthawk/run_reconstructed_model.py
nighthawk/test_model_application.py
nighthawk/saved_model_with_preprocessing/keras_metadata.pb
nighthawk/saved_model_with_preprocessing/saved_model.pb
nighthawk/saved_model_with_preprocessing/variables/variables.data-00000-of-00001
nighthawk/saved_model_with_preprocessing/variables/variables.index
nighthawk/taxonomy/IBP-AOS-LIST21.csv
nighthawk/taxonomy/ebird_taxonomy.csv
nighthawk/taxonomy/families.txt
nighthawk/taxonomy/groups.txt
nighthawk/taxonomy/groups_ebird_codes.csv
nighthawk/taxonomy/orders.txt
nighthawk/taxonomy/species.txt
nighthawk/taxonomy/taxonomy_version.txt
nighthawk/test_config/probability_calibrations.csv
nighthawk/test_config/test_config.json
nighthawk/test_config/test_set_performance/taxon_summary_family.csv
nighthawk/test_config/test_set_performance/taxon_summary_group.csv
nighthawk/test_config/test_set_performance/taxon_summary_order.csv
nighthawk/test_config/test_set_performance/taxon_summary_species.csv
nighthawk-0.3.1.dist-info/METADATA
nighthawk-0.3.1.dist-info/WHEEL
nighthawk-0.3.1.dist-info/entry_points.txt
nighthawk-0.3.1.dist-info/licenses/LICENSE
nighthawk-0.3.1.dist-info/RECORD
