Metadata-Version: 2.4
Name: nighthawk
Version: 0.3.1
Summary: Nighthawk avian nocturnal flight call detector
Project-URL: Bug Tracker, https://github.com/bmvandoren/nighthawk/issues
Project-URL: Source Code, https://github.com/bmvandoren/nighthawk
Author-email: Benjamin Van Doren <vandoren@cornell.edu>
License: 
License-File: LICENSE
Classifier: Operating System :: OS Independent
Classifier: Programming Language :: Python :: 3
Requires-Python: ~=3.10.0
Requires-Dist: librosa~=0.10.0
Requires-Dist: pandas~=2.2.0
Requires-Dist: pyyaml
Requires-Dist: tensorflow-macos~=2.12.0; platform_system == 'Darwin' and platform_machine == 'arm64'
Requires-Dist: tensorflow~=2.12.0; platform_system != 'Darwin' or platform_machine != 'arm64'
